adafruit_circuitpython_wsgi-3.0.3.dist-info/licenses/LICENSE
adafruit_wsgi/__init__.py
adafruit_wsgi/esp32spi_wsgiserver.py
adafruit_wsgi/request.py
adafruit_wsgi/wsgi_app.py
adafruit_circuitpython_wsgi-3.0.3.dist-info/METADATA
adafruit_circuitpython_wsgi-3.0.3.dist-info/WHEEL
adafruit_circuitpython_wsgi-3.0.3.dist-info/top_level.txt
adafruit_circuitpython_wsgi-3.0.3.dist-info/RECORD
