Metadata-Version: 2.4
Name: adafruit-circuitpython-wsgi
Version: 3.0.3
Summary: CircuitPython framework for creating WSGI compatible web server applications.
Author-email: Adafruit Industries <circuitpython@adafruit.com>
License: MIT
Project-URL: Homepage, https://github.com/adafruit/Adafruit_CircuitPython_WSGI
Keywords: adafruit,blinka,circuitpython,micropython,wsgi,web,server,webserver,app,webapp,framework,http,https,flask
Classifier: Intended Audience :: Developers
Classifier: Topic :: Software Development :: Libraries
Classifier: Topic :: Software Development :: Embedded Systems
Classifier: Topic :: System :: Hardware
Classifier: License :: OSI Approved :: MIT License
Classifier: Programming Language :: Python :: 3
License-File: LICENSE
Requires-Dist: Adafruit-Blinka
Provides-Extra: optional
Dynamic: license-file
